plain/CHANGELOG.md
plain/README.md
plain/__main__.py
plain/debug.py
plain/exceptions.py
plain/json.py
plain/paginator.py
plain/signing.py
plain/validators.py
plain/wsgi.py
plain/agents/.claude/rules/plain-templates.md
plain/agents/.claude/rules/plain.md
plain/agents/.claude/skills/plain-install/SKILL.md
plain/agents/.claude/skills/plain-upgrade/SKILL.md
plain/assets/README.md
plain/assets/__init__.py
plain/assets/compile.py
plain/assets/finders.py
plain/assets/fingerprints.py
plain/assets/urls.py
plain/assets/views.py
plain/chores/README.md
plain/chores/__init__.py
plain/chores/core.py
plain/chores/registry.py
plain/cli/README.md
plain/cli/__init__.py
plain/cli/agent.py
plain/cli/build.py
plain/cli/changelog.py
plain/cli/chores.py
plain/cli/core.py
plain/cli/docs.py
plain/cli/formatting.py
plain/cli/install.py
plain/cli/llmdocs.py
plain/cli/output.py
plain/cli/preflight.py
plain/cli/print.py
plain/cli/registry.py
plain/cli/request.py
plain/cli/runtime.py
plain/cli/scaffold.py
plain/cli/server.py
plain/cli/settings.py
plain/cli/shell.py
plain/cli/startup.py
plain/cli/upgrade.py
plain/cli/urls.py
plain/cli/utils.py
plain/csrf/README.md
plain/csrf/middleware.py
plain/forms/README.md
plain/forms/__init__.py
plain/forms/boundfield.py
plain/forms/exceptions.py
plain/forms/fields.py
plain/forms/forms.py
plain/http/README.md
plain/http/__init__.py
plain/http/cookie.py
plain/http/exceptions.py
plain/http/middleware.py
plain/http/multipartparser.py
plain/http/request.py
plain/http/response.py
plain/internal/__init__.py
plain/internal/reloader.py
plain/internal/files/__init__.py
plain/internal/files/base.py
plain/internal/files/locks.py
plain/internal/files/move.py
plain/internal/files/temp.py
plain/internal/files/uploadedfile.py
plain/internal/files/uploadhandler.py
plain/internal/files/utils.py
plain/internal/handlers/__init__.py
plain/internal/handlers/base.py
plain/internal/handlers/exception.py
plain/internal/handlers/wsgi.py
plain/internal/middleware/__init__.py
plain-0.103.1.dist-info/METADATA
plain-0.103.1.dist-info/WHEEL
plain-0.103.1.dist-info/entry_points.txt
plain-0.103.1.dist-info/licenses/LICENSE
plain-0.103.1.dist-info/RECORD
