Metadata-Version: 2.4
Name: plain
Version: 0.103.1
Summary: A web framework for building products with Python.
Author-email: Dave Gaeddert <dave.gaeddert@dropseed.dev>
License-Expression: BSD-3-Clause
License-File: LICENSE
Requires-Python: >=3.13
Requires-Dist: click>=8.0.0
Requires-Dist: jinja2>=3.1.2
Requires-Dist: opentelemetry-api>=1.34.1
Requires-Dist: opentelemetry-semantic-conventions>=0.55b1
Requires-Dist: watchfiles>=0.18.0
